tkinter_temps/__init__.py
tkinter_temps-1.0.3.dist-info/LICENSE
tkinter_temps-1.0.3.dist-info/METADATA
tkinter_temps-1.0.3.dist-info/WHEEL
tkinter_temps-1.0.3.dist-info/top_level.txt
tkinter_temps-1.0.3.dist-info/RECORD
