Metadata-Version: 2.1
Name: tkinter-temps
Version: 1.0.3
Summary: A module for ease of making GUI's in Tkinter
Home-page: https://www.beyonce.com
Author: hunterg
Author-email: redissuslolol@gmail.com
License: UNKNOWN
Platform: UNKNOWN
Classifier: Programming Language :: Python :: 3
Classifier: License :: OSI Approved :: MIT License
Classifier: Operating System :: OS Independent
Requires-Python: >=3.6
Requires-Dist: docifyPLUS
Requires-Dist: lambdaChaining
